CHANGES.txt
CONTRIBUTORS.txt
MANIFEST.in
README.txt
setup.py
docs/LICENSE
src/templer/__init__.py
src/templer.localcommands.egg-info/PKG-INFO
src/templer.localcommands.egg-info/SOURCES.txt
src/templer.localcommands.egg-info/dependency_links.txt
src/templer.localcommands.egg-info/entry_points.txt
src/templer.localcommands.egg-info/namespace_packages.txt
src/templer.localcommands.egg-info/not-zip-safe
src/templer.localcommands.egg-info/requires.txt
src/templer.localcommands.egg-info/top_level.txt
src/templer/localcommands/__init__.py
src/templer/localcommands/command.py
src/templer/localcommands/template.py
src/templer/localcommands/tests/__init__.py
src/templer/localcommands/tests/test_localcommand.py